dpt_logging/__init__.py
dpt_logging/abstract_log_handler.py
dpt_logging/exception_log_trap.py
dpt_logging/log_handler.py
dpt_logging/log_line.py
dpt_logging-1.1.2.data/data/docs/LICENSE
dpt_logging-1.1.2.data/data/docs/README
dpt_logging-1.1.2.dist-info/LICENSE
dpt_logging-1.1.2.dist-info/METADATA
dpt_logging-1.1.2.dist-info/WHEEL
dpt_logging-1.1.2.dist-info/top_level.txt
dpt_logging-1.1.2.dist-info/RECORD
