Metadata-Version: 2.1
Name: dpt-logging
Version: 1.1.2
Summary: An extendable logging mechanism implementation
Home-page: https://www.direct-netware.de/redirect?dpt;logging
Author: direct Netware Group et al.
Author-email: web@direct-netware.de
License: MPL2
Platform: any
Classifier: Intended Audience :: Developers
Classifier: License :: OSI Approved :: Mozilla Public License 2.0 (MPL 2.0)
Classifier: Operating System :: OS Independent
Classifier: Programming Language :: Python
Classifier: Topic :: Software Development :: Libraries :: Python Modules
Requires-Dist: dpt-module-loader (<2,>=1)
Requires-Dist: dpt-runtime (<3,>=2.1.0)
Requires-Dist: dpt-threading (<3,>=2)
